proxyproviders/__init__.py
proxyproviders/algorithms.py
proxyproviders/exceptions.py
proxyproviders/models/__init__.py
proxyproviders/models/proxy.py
proxyproviders/providers/brightdata.py
proxyproviders/providers/webshare.py
proxyproviders/proxy_provider.py
proxyproviders-0.2.0.dist-info/METADATA
proxyproviders-0.2.0.dist-info/WHEEL
proxyproviders-0.2.0.dist-info/licenses/LICENSE
proxyproviders-0.2.0.dist-info/RECORD
