Metadata-Version: 2.4
Name: proxyproviders
Version: 0.2.0
Summary: A unified interface for different proxy providers
License: MIT License
License-File: LICENSE
Author: David Teather
Author-email: contact.davidteather@gmail.com
Requires-Python: >=3.9
Classifier: Development Status :: 3 - Alpha
Classifier: Intended Audience :: Developers
Classifier: License :: OSI Approved :: MIT License
Classifier: Programming Language :: Python :: 3
Provides-Extra: dev
Requires-Dist: black ; extra == "dev"
Requires-Dist: coverage ; extra == "dev"
Requires-Dist: mypy ; extra == "dev"
Requires-Dist: pytest ; extra == "dev"
Requires-Dist: requests
Requires-Dist: sphinx ; extra == "dev"
Requires-Dist: toml ; extra == "dev"
Requires-Dist: types-requests ; extra == "dev"
